[
  {
    "pulaar": "A jaaraama",
    "english":"I greet you."
  },
  {
    "pulaar": "On jaaraama",  "english":"I greet you (respectful)"
  },
  {
    "pulaar": "Tanaa alaa", "english":"Is there no evil?"
  },
  {
    "pulaar": "Tanaa alaa ton", "english":"Is there no evil there?"
  },
  {
    "pulaar": "Tanaa alaa gaa","english": "is there no evil here"
  },
  {
    "pulaar": "Jam tun","english": "Peace only"
  },
  {
    "pulaar": "No wa’i?", "english":"what’s up"
  },
  {
    "pulaar": "No marsude","english": "now is it going?"
  },
  {
    "pulaar": "No marsude seeda", "english":"I’m so & so"
  },
  {
    "pulaar": "No marsude fota", "english":"I’m fine great."
  },
  {
    "pulaar": "Beynguure nden no e jam?", "english":"is the family well?"
  },
  {
    "pulaar": "Faybe ben no e jam?","english": "are the children well"
  },
  {
    "pulaar": "Boobo on no selli", "english":"is your baby healthy?"
  },
  {
    "pulaar": "Ko honno beyngu maa wadi","english": "how is your wife doing"
  },
  {
    "pulaar": "Golle den?","english": "and your work"
  },
  {
    "pulaar": "A waalii e jam", "english":"did you sleep in peace"
  },
  {
    "pulaar": "On belike e jam", "english":"did you sleep in peace respectfully"
  },
  {
    "pulaar": "On nallii e jam","english": "have you spend the day in peace"
  },
  {
    "pulaar": "On hiirii e jam","english": "have you spend the evening in peace"
  },
  {
    "pulaar": "Hida e jam", "english":"are you well"
  },
  {
    "pulaar": "Kori hidon e jam", "english":"I hope you are well? Respectful"
  },
  {
    "pulaar": "Onon le?", "english":"and you?"
  },
  {
    "pulaar": "Hibe e jam", "english": "they are well"
  },
  {
    "pulaar": "Ko yettude Alla", "english": "thanks be to God"
  },
  {
    "pulaar": "Alhamdulilahi","english": "Thanks to be God"
  },
  {
    "pulaar": "Oo-o","english": "No"
  },
  {
    "pulaar": "En janngo", "english":"see you tomorrow"
  },
  {
    "pulaar": "En bimmbi","english": "see you in the morning"
  },
  {
    "pulaar": "En ontuma", "english":"see you later"
  },
  {
    "pulaar": "En nalorma","english": "see you later today"
  },
  {
    "pulaar": "En kiikiide","english": "see you this afternoon"
  },
  {
    "pulaar": "En jemma", "english":"see you tonight"
  },
  {
    "pulaar": "Si Alla jabi","english": "god willing"
  },
  {
    "pulaar": "A jaaraama, nani?","english": "thanks, hear?"
  },
  {
    "pulaar": "Nallen e jam","english": "let’s pass the day in peace"
  },
  {
    "pulaar": "Hiiren e jam","english": "let’s pass the evening in peace"
  },
  {
    "pulaar": "Waleen e jam","english": "let us sleep well"
  },
  {
    "pulaar": "Beloden e jam","english": "let us sleep well respectful"
  },
  {
    "pulaar": "Hii-hi, Eyyo",  "english":"yes"
  },
  {
    "pulaar": "O’o, O’owooye","english": "No"
  },
  {
    "pulaar": "A jaaraama", "english": "thank you"
  },
  {
    "pulaar": "Awa","english": "Ok"
  },
  {
    "pulaar": "Accee hakkee", "english":"please excuse me"
  },
  {
    "pulaar": "Pular an Lannii!", "english":"that’s all the Pular I know!"
  },
  {
    "pulaar": "Mi waawaa Pular buy","english": "I don’t speak much pular"
  },
  {
    "pulaar": "Mido waawi pular seeda tun", "english":"I speak Pular small small"
  },
  {
    "pulaar": "Mi faamaali", "english":"I don’t understand"
  },
  {
    "pulaar": "Mido ekkitaade", "english": "I am learning"
  },
  {
    "pulaar": "Mi neebaali gaa", "english": "I just got here"
  },
  {
    "pulaar": "Munno neebataa mi waawa", "english": "Be patient, I’ll learn soon"
  },
  {
    "pulaar": "Mido ekkitaade haala faransi taho",  "english":"I need to learn French first"
  }
]